westat/__init__.py
westat/dataframe_to_table.py
westat/dataset.py
westat/logger.py
westat/assess/__init__.py
westat/assess/get_auc.py
westat/assess/get_auc_by_card.py
westat/assess/get_data_psi.py
westat/assess/get_ks.py
westat/assess/get_ks_by_card.py
westat/assess/get_psi.py
westat/assess/get_score_distribution.py
westat/assess/get_vif.py
westat/assess/plot_auc.py
westat/assess/plot_ks.py
westat/assess/plot_lift.py
westat/assess/plot_roc_ks.py
westat/core/Scorecard.py
westat/core/__init__.py
westat/core/column.py
westat/core/table.py
westat/data/CreditCard.xls
westat/data/UCI_Credit_Card.csv
westat/data/GiveMeSomeCredit/Data Dictionary.xls
westat/data/GiveMeSomeCredit/cs-test.csv
westat/data/GiveMeSomeCredit/cs-training.csv
westat/data/GiveMeSomeCredit/sampleEntry.csv
westat/explore/__init__.py
westat/explore/check_data_target.py
westat/explore/get_data_check.py
westat/explore/get_data_describe.py
westat/explore/get_data_distribution.py
westat/explore/plot_counts.py
westat/explore/proc_means.py
westat/model/__init__.py
westat/model/ahp.py
westat/model/chi_square.py
westat/model/feature_selection.py
westat/model/finance.py
westat/model/get_bins.py
westat/model/get_data_bins.py
westat/model/get_data_discrete.py
westat/model/get_data_iv.py
westat/model/get_data_type.py
westat/model/get_data_woe.py
westat/model/get_entropy.py
westat/model/get_model_iv.py
westat/model/get_predict_score.py
westat/model/get_scorecard.py
westat/model/get_tree_bins.py
westat/model/get_woe_iv.py
westat/model/get_woe_transform.py
westat/model/gini_impurity.py
westat/model/logistic.py
westat/model/plot_corr.py
westat/model/plot_iv.py
westat/model/plot_woe.py
westat/model/statistic.py
westat/model/stepwise_forward.py
westat/model/stepwise_lr.py
westat/model/tree/__init__.py
westat/model/tree/plot_tree.py
westat/model/tree/tree_to_img.py
westat/model/tree/tree_to_pdf.py
westat/model/tree/graphviz/__init__.py
westat/model/tree/graphviz/_compat.py
westat/model/tree/graphviz/_defaults.py
westat-0.3.3.dist-info/METADATA
westat-0.3.3.dist-info/WHEEL
westat-0.3.3.dist-info/licenses/LICENSE
westat-0.3.3.dist-info/RECORD
