Metadata-Version: 2.3
Name: westat
Version: 0.3.3
Summary: A package for stat and data miner,calculate woe and iv,and plot woe ,plot iv,calculate ks ,plot ks and auc,plot roc
Project-URL: homepage, http://www.pyminer.com
Project-URL: documentation, https://westat.readthedocs.io
Project-URL: repository, https://gitee.com/westat/westat
Author-email: westat <westat@foxmail.com>
License-File: LICENSE
Keywords: auc,iv,ks,lift,psi,roc,scorecard,woe
Classifier: Development Status :: 3 - Alpha
Classifier: Environment :: Console
Classifier: Intended Audience :: Science/Research
Classifier: License :: OSI Approved :: GNU General Public License v3 (GPLv3)
Classifier: Operating System :: OS Independent
Classifier: Programming Language :: Python :: 3
Classifier: Topic :: Scientific/Engineering
Requires-Python: >=3.7
Requires-Dist: ipywidgets
Requires-Dist: matplotlib
Requires-Dist: numpy
Requires-Dist: openpyxl
Requires-Dist: optbinning
Requires-Dist: pandas
Requires-Dist: scikit-learn
Requires-Dist: statsmodels
Requires-Dist: tqdm
